[
  {
    "hex": "#784140",
    "rgb": "rgb(120, 65, 64)",
    "category": "red",
    "id": 1
  },
  {
    "hex": "#aa514d",
    "rgb": "rgb(170, 81, 77)",
    "category": "red",
    "id": 2
  },
  {
    "hex": "#a03833",
    "rgb": "rgb(160, 56, 51)",
    "category": "red",
    "id": 3
  },
  {
    "hex": "#8e4742",
    "rgb": "rgb(142, 71, 66)",
    "category": "red",
    "id": 4
  },
  {
    "hex": "#793731",
    "rgb": "rgb(121, 55, 49)",
    "category": "red",
    "id": 5
  },
  {
    "hex": "#9d493f",
    "rgb": "rgb(157, 73, 63)",
    "category": "red",
    "id": 6
  },
  {
    "hex": "#8c3327",
    "rgb": "rgb(140, 51, 39)",
    "category": "red",
    "id": 7
  },
  {
    "hex": "#9d594e",
    "rgb": "rgb(157, 89, 78)",
    "category": "red",
    "id": 8
  },
  {
    "hex": "#76453c",
    "rgb": "rgb(118, 69, 60)",
    "category": "red",
    "id": 9
  },
  {
    "hex": "#914b3d",
    "rgb": "rgb(145, 75, 61)",
    "category": "red",
    "id": 10
  },
  {
    "hex": "#b04e38",
    "rgb": "rgb(176, 78, 56)",
    "category": "red",
    "id": 11
  },
  {
    "hex": "#99432e",
    "rgb": "rgb(153, 67, 46)",
    "category": "red",
    "id": 12
  },
  {
    "hex": "#8f4b38",
    "rgb": "rgb(143, 75, 56)",
    "category": "red",
    "id": 13
  },
  {
    "hex": "#95462e",
    "rgb": "rgb(149, 70, 46)",
    "category": "red",
    "id": 14
  },
  {
    "hex": "#8c5745",
    "rgb": "rgb(140, 87, 69)",
    "category": "red",
    "id": 15
  },
  {
    "hex": "#965a44",
    "rgb": "rgb(150, 90, 68)",
    "category": "red",
    "id": 16
  },
  {
    "hex": "#986450",
    "rgb": "rgb(152, 100, 80)",
    "category": "red",
    "id": 17
  },
  {
    "hex": "#c56035",
    "rgb": "rgb(197, 96, 53)",
    "category": "red",
    "id": 18
  },
  {
    "hex": "#6e4b3b",
    "rgb": "rgb(110, 75, 59)",
    "category": "red",
    "id": 19
  },
  {
    "hex": "#9f512a",
    "rgb": "rgb(159, 81, 42)",
    "category": "red",
    "id": 20
  },
  {
    "hex": "#b96c42",
    "rgb": "rgb(185, 108, 66)",
    "category": "red",
    "id": 21
  },
  {
    "hex": "#764225",
    "rgb": "rgb(118, 66, 37)",
    "category": "red",
    "id": 22
  },
  {
    "hex": "#93674b",
    "rgb": "rgb(147, 103, 75)",
    "category": "red",
    "id": 23
  },
  {
    "hex": "#86522f",
    "rgb": "rgb(134, 82, 47)",
    "category": "red",
    "id": 24
  },
  {
    "hex": "#ba6c33",
    "rgb": "rgb(186, 108, 51)",
    "category": "red",
    "id": 25
  },
  {
    "hex": "#8e6749",
    "rgb": "rgb(142, 103, 73)",
    "category": "red",
    "id": 26
  },
  {
    "hex": "#966339",
    "rgb": "rgb(150, 99, 57)",
    "category": "red",
    "id": 27
  },
  {
    "hex": "#c87a35",
    "rgb": "rgb(200, 122, 53)",
    "category": "red",
    "id": 28
  },
  {
    "hex": "#a86f39",
    "rgb": "rgb(168, 111, 57)",
    "category": "red",
    "id": 29
  },
  {
    "hex": "#8b6642",
    "rgb": "rgb(139, 102, 66)",
    "category": "yellow",
    "id": 30
  },
  {
    "hex": "#b07536",
    "rgb": "rgb(176, 117, 54)",
    "category": "yellow",
    "id": 31
  },
  {
    "hex": "#a17646",
    "rgb": "rgb(161, 118, 70)",
    "category": "yellow",
    "id": 32
  },
  {
    "hex": "#6e512f",
    "rgb": "rgb(110, 81, 47)",
    "category": "yellow",
    "id": 33
  },
  {
    "hex": "#a77a40",
    "rgb": "rgb(167, 122, 64)",
    "category": "yellow",
    "id": 34
  },
  {
    "hex": "#856b46",
    "rgb": "rgb(133, 107, 70)",
    "category": "yellow",
    "id": 35
  },
  {
    "hex": "#aa8651",
    "rgb": "rgb(170, 134, 81)",
    "category": "yellow",
    "id": 36
  },
  {
    "hex": "#b38842",
    "rgb": "rgb(179, 136, 66)",
    "category": "yellow",
    "id": 37
  },
  {
    "hex": "#a87d33",
    "rgb": "rgb(168, 125, 51)",
    "category": "yellow",
    "id": 38
  },
  {
    "hex": "#7b5f2a",
    "rgb": "rgb(123, 95, 42)",
    "category": "yellow",
    "id": 39
  },
  {
    "hex": "#917742",
    "rgb": "rgb(145, 119, 66)",
    "category": "yellow",
    "id": 40
  },
  {
    "hex": "#78612e",
    "rgb": "rgb(120, 97, 46)",
    "category": "yellow",
    "id": 41
  },
  {
    "hex": "#675834",
    "rgb": "rgb(103, 88, 52)",
    "category": "yellow",
    "id": 42
  },
  {
    "hex": "#a8852d",
    "rgb": "rgb(168, 133, 45)",
    "category": "yellow",
    "id": 43
  },
  {
    "hex": "#a38535",
    "rgb": "rgb(163, 133, 53)",
    "category": "yellow",
    "id": 44
  },
  {
    "hex": "#726232",
    "rgb": "rgb(114, 98, 50)",
    "category": "yellow",
    "id": 45
  },
  {
    "hex": "#ae943c",
    "rgb": "rgb(174, 148, 60)",
    "category": "yellow",
    "id": 46
  },
  {
    "hex": "#84743a",
    "rgb": "rgb(132, 116, 58)",
    "category": "yellow",
    "id": 47
  },
  {
    "hex": "#7a6b32",
    "rgb": "rgb(122, 107, 50)",
    "category": "yellow",
    "id": 48
  },
  {
    "hex": "#918036",
    "rgb": "rgb(145, 128, 54)",
    "category": "yellow",
    "id": 49
  },
  {
    "hex": "#a08e32",
    "rgb": "rgb(160, 142, 50)",
    "category": "yellow",
    "id": 50
  },
  {
    "hex": "#9c9153",
    "rgb": "rgb(156, 145, 83)",
    "category": "yellow",
    "id": 51
  },
  {
    "hex": "#9a8e3b",
    "rgb": "rgb(154, 142, 59)",
    "category": "yellow",
    "id": 52
  },
  {
    "hex": "#8e832f",
    "rgb": "rgb(142, 131, 47)",
    "category": "yellow",
    "id": 53
  },
  {
    "hex": "#80782e",
    "rgb": "rgb(128, 120, 46)",
    "category": "yellow",
    "id": 54
  },
  {
    "hex": "#98924f",
    "rgb": "rgb(152, 146, 79)",
    "category": "yellow",
    "id": 55
  },
  {
    "hex": "#a79f3b",
    "rgb": "rgb(167, 159, 59)",
    "category": "yellow",
    "id": 56
  },
  {
    "hex": "#827e31",
    "rgb": "rgb(130, 126, 49)",
    "category": "yellow",
    "id": 57
  },
  {
    "hex": "#696736",
    "rgb": "rgb(105, 103, 54)",
    "category": "yellow",
    "id": 58
  },
  {
    "hex": "#c8c532",
    "rgb": "rgb(200, 197, 50)",
    "category": "yellow",
    "id": 59
  },
  {
    "hex": "#9c9c52",
    "rgb": "rgb(156, 156, 82)",
    "category": "yellow",
    "id": 60
  },
  {
    "hex": "#989940",
    "rgb": "rgb(152, 153, 64)",
    "category": "yellow",
    "id": 61
  },
  {
    "hex": "#777a31",
    "rgb": "rgb(119, 122, 49)",
    "category": "yellow",
    "id": 62
  },
  {
    "hex": "#7c8033",
    "rgb": "rgb(124, 128, 51)",
    "category": "yellow",
    "id": 63
  },
  {
    "hex": "#696d37",
    "rgb": "rgb(105, 109, 55)",
    "category": "yellow",
    "id": 64
  },
  {
    "hex": "#9da452",
    "rgb": "rgb(157, 164, 82)",
    "category": "yellow",
    "id": 65
  },
  {
    "hex": "#9aa34e",
    "rgb": "rgb(154, 163, 78)",
    "category": "yellow",
    "id": 66
  },
  {
    "hex": "#97a051",
    "rgb": "rgb(151, 160, 81)",
    "category": "yellow",
    "id": 67
  },
  {
    "hex": "#92a131",
    "rgb": "rgb(146, 161, 49)",
    "category": "yellow",
    "id": 68
  },
  {
    "hex": "#7b8a26",
    "rgb": "rgb(123, 138, 38)",
    "category": "yellow",
    "id": 69
  },
  {
    "hex": "#9aad38",
    "rgb": "rgb(154, 173, 56)",
    "category": "yellow",
    "id": 70
  },
  {
    "hex": "#7d8d3a",
    "rgb": "rgb(125, 141, 58)",
    "category": "yellow",
    "id": 71
  },
  {
    "hex": "#869a36",
    "rgb": "rgb(134, 154, 54)",
    "category": "yellow",
    "id": 72
  },
  {
    "hex": "#96aa51",
    "rgb": "rgb(150, 170, 81)",
    "category": "yellow",
    "id": 73
  },
  {
    "hex": "#6c8129",
    "rgb": "rgb(108, 129, 41)",
    "category": "yellow",
    "id": 74
  },
  {
    "hex": "#82944a",
    "rgb": "rgb(130, 148, 74)",
    "category": "yellow",
    "id": 75
  },
  {
    "hex": "#86a433",
    "rgb": "rgb(134, 164, 51)",
    "category": "yellow",
    "id": 76
  },
  {
    "hex": "#728e29",
    "rgb": "rgb(114, 142, 41)",
    "category": "yellow",
    "id": 77
  },
  {
    "hex": "#728f2e",
    "rgb": "rgb(114, 143, 46)",
    "category": "yellow",
    "id": 78
  },
  {
    "hex": "#7e9945",
    "rgb": "rgb(126, 153, 69)",
    "category": "yellow",
    "id": 79
  },
  {
    "hex": "#6e9127",
    "rgb": "rgb(110, 145, 39)",
    "category": "yellow",
    "id": 80
  },
  {
    "hex": "#90c134",
    "rgb": "rgb(144, 193, 52)",
    "category": "yellow",
    "id": 81
  },
  {
    "hex": "#5d792e",
    "rgb": "rgb(93, 121, 46)",
    "category": "yellow",
    "id": 82
  },
  {
    "hex": "#759f30",
    "rgb": "rgb(117, 159, 48)",
    "category": "yellow",
    "id": 83
  },
  {
    "hex": "#5f7b36",
    "rgb": "rgb(95, 123, 54)",
    "category": "yellow",
    "id": 84
  },
  {
    "hex": "#526d2c",
    "rgb": "rgb(82, 109, 44)",
    "category": "yellow",
    "id": 85
  },
  {
    "hex": "#7ca447",
    "rgb": "rgb(124, 164, 71)",
    "category": "yellow",
    "id": 86
  },
  {
    "hex": "#688c3b",
    "rgb": "rgb(104, 140, 59)",
    "category": "yellow",
    "id": 87
  },
  {
    "hex": "#578226",
    "rgb": "rgb(87, 130, 38)",
    "category": "yellow",
    "id": 88
  },
  {
    "hex": "#65982f",
    "rgb": "rgb(101, 152, 47)",
    "category": "yellow",
    "id": 89
  },
  {
    "hex": "#749c4c",
    "rgb": "rgb(116, 156, 76)",
    "category": "green",
    "id": 90
  },
  {
    "hex": "#5b7f3a",
    "rgb": "rgb(91, 127, 58)",
    "category": "green",
    "id": 91
  },
  {
    "hex": "#4c7528",
    "rgb": "rgb(76, 117, 40)",
    "category": "green",
    "id": 92
  },
  {
    "hex": "#567c37",
    "rgb": "rgb(86, 124, 55)",
    "category": "green",
    "id": 93
  },
  {
    "hex": "#548b2a",
    "rgb": "rgb(84, 139, 42)",
    "category": "green",
    "id": 94
  },
  {
    "hex": "#4f6e39",
    "rgb": "rgb(79, 110, 57)",
    "category": "green",
    "id": 95
  },
  {
    "hex": "#5f8646",
    "rgb": "rgb(95, 134, 70)",
    "category": "green",
    "id": 96
  },
  {
    "hex": "#66a73e",
    "rgb": "rgb(102, 167, 62)",
    "category": "green",
    "id": 97
  },
  {
    "hex": "#5d903f",
    "rgb": "rgb(93, 144, 63)",
    "category": "green",
    "id": 98
  },
  {
    "hex": "#4e723a",
    "rgb": "rgb(78, 114, 58)",
    "category": "green",
    "id": 99
  },
  {
    "hex": "#6aa64b",
    "rgb": "rgb(106, 166, 75)",
    "category": "green",
    "id": 100
  },
  {
    "hex": "#4d922d",
    "rgb": "rgb(77, 146, 45)",
    "category": "green",
    "id": 101
  },
  {
    "hex": "#59b033",
    "rgb": "rgb(89, 176, 51)",
    "category": "green",
    "id": 102
  },
  {
    "hex": "#558642",
    "rgb": "rgb(85, 134, 66)",
    "category": "green",
    "id": 103
  },
  {
    "hex": "#569041",
    "rgb": "rgb(86, 144, 65)",
    "category": "green",
    "id": 104
  },
  {
    "hex": "#58a43e",
    "rgb": "rgb(88, 164, 62)",
    "category": "green",
    "id": 105
  },
  {
    "hex": "#58bf39",
    "rgb": "rgb(88, 191, 57)",
    "category": "green",
    "id": 106
  },
  {
    "hex": "#48783a",
    "rgb": "rgb(72, 120, 58)",
    "category": "green",
    "id": 107
  },
  {
    "hex": "#4c873d",
    "rgb": "rgb(76, 135, 61)",
    "category": "green",
    "id": 108
  },
  {
    "hex": "#378625",
    "rgb": "rgb(55, 134, 37)",
    "category": "green",
    "id": 109
  },
  {
    "hex": "#417a35",
    "rgb": "rgb(65, 122, 53)",
    "category": "green",
    "id": 110
  },
  {
    "hex": "#42ae2f",
    "rgb": "rgb(66, 174, 47)",
    "category": "green",
    "id": 111
  },
  {
    "hex": "#4cc23a",
    "rgb": "rgb(76, 194, 58)",
    "category": "green",
    "id": 112
  },
  {
    "hex": "#5aa750",
    "rgb": "rgb(90, 167, 80)",
    "category": "green",
    "id": 113
  },
  {
    "hex": "#308926",
    "rgb": "rgb(48, 137, 38)",
    "category": "green",
    "id": 114
  },
  {
    "hex": "#438c3c",
    "rgb": "rgb(67, 140, 60)",
    "category": "green",
    "id": 115
  },
  {
    "hex": "#38b92f",
    "rgb": "rgb(56, 185, 47)",
    "category": "green",
    "id": 116
  },
  {
    "hex": "#41783e",
    "rgb": "rgb(65, 120, 62)",
    "category": "green",
    "id": 117
  },
  {
    "hex": "#458942",
    "rgb": "rgb(69, 137, 66)",
    "category": "green",
    "id": 118
  },
  {
    "hex": "#479846",
    "rgb": "rgb(71, 152, 70)",
    "category": "green",
    "id": 119
  },
  {
    "hex": "#278427",
    "rgb": "rgb(39, 132, 39)",
    "category": "green",
    "id": 120
  },
  {
    "hex": "#34ca37",
    "rgb": "rgb(52, 202, 55)",
    "category": "green",
    "id": 121
  },
  {
    "hex": "#48934b",
    "rgb": "rgb(72, 147, 75)",
    "category": "green",
    "id": 122
  },
  {
    "hex": "#28762c",
    "rgb": "rgb(40, 118, 44)",
    "category": "green",
    "id": 123
  },
  {
    "hex": "#3cc045",
    "rgb": "rgb(60, 192, 69)",
    "category": "green",
    "id": 124
  },
  {
    "hex": "#37c242",
    "rgb": "rgb(55, 194, 66)",
    "category": "green",
    "id": 125
  },
  {
    "hex": "#33c242",
    "rgb": "rgb(51, 194, 66)",
    "category": "green",
    "id": 126
  },
  {
    "hex": "#44ad50",
    "rgb": "rgb(68, 173, 80)",
    "category": "green",
    "id": 127
  },
  {
    "hex": "#3fb74f",
    "rgb": "rgb(63, 183, 79)",
    "category": "green",
    "id": 128
  },
  {
    "hex": "#42894d",
    "rgb": "rgb(66, 137, 77)",
    "category": "green",
    "id": 129
  },
  {
    "hex": "#47a757",
    "rgb": "rgb(71, 167, 87)",
    "category": "green",
    "id": 130
  },
  {
    "hex": "#42834e",
    "rgb": "rgb(66, 131, 78)",
    "category": "green",
    "id": 131
  },
  {
    "hex": "#448250",
    "rgb": "rgb(68, 130, 80)",
    "category": "green",
    "id": 132
  },
  {
    "hex": "#4ab060",
    "rgb": "rgb(74, 176, 96)",
    "category": "green",
    "id": 133
  },
  {
    "hex": "#387045",
    "rgb": "rgb(56, 112, 69)",
    "category": "green",
    "id": 134
  },
  {
    "hex": "#2b723d",
    "rgb": "rgb(43, 114, 61)",
    "category": "green",
    "id": 135
  },
  {
    "hex": "#4a9e61",
    "rgb": "rgb(74, 158, 97)",
    "category": "green",
    "id": 136
  },
  {
    "hex": "#28743e",
    "rgb": "rgb(40, 116, 62)",
    "category": "green",
    "id": 137
  },
  {
    "hex": "#26733d",
    "rgb": "rgb(38, 115, 61)",
    "category": "green",
    "id": 138
  },
  {
    "hex": "#33bb5e",
    "rgb": "rgb(51, 187, 94)",
    "category": "green",
    "id": 139
  },
  {
    "hex": "#52a16d",
    "rgb": "rgb(82, 161, 109)",
    "category": "green",
    "id": 140
  },
  {
    "hex": "#389a5a",
    "rgb": "rgb(56, 154, 90)",
    "category": "green",
    "id": 141
  },
  {
    "hex": "#2d7548",
    "rgb": "rgb(45, 117, 72)",
    "category": "green",
    "id": 142
  },
  {
    "hex": "#49b271",
    "rgb": "rgb(73, 178, 113)",
    "category": "green",
    "id": 143
  },
  {
    "hex": "#39a263",
    "rgb": "rgb(57, 162, 99)",
    "category": "green",
    "id": 144
  },
  {
    "hex": "#2e8d56",
    "rgb": "rgb(46, 141, 86)",
    "category": "green",
    "id": 145
  },
  {
    "hex": "#378d5c",
    "rgb": "rgb(55, 141, 92)",
    "category": "green",
    "id": 146
  },
  {
    "hex": "#33895a",
    "rgb": "rgb(51, 137, 90)",
    "category": "green",
    "id": 147
  },
  {
    "hex": "#47936a",
    "rgb": "rgb(71, 147, 106)",
    "category": "green",
    "id": 148
  },
  {
    "hex": "#357d58",
    "rgb": "rgb(53, 125, 88)",
    "category": "green",
    "id": 149
  },
  {
    "hex": "#369465",
    "rgb": "rgb(54, 148, 101)",
    "category": "cyan",
    "id": 150
  },
  {
    "hex": "#2b6e4e",
    "rgb": "rgb(43, 110, 78)",
    "category": "cyan",
    "id": 151
  },
  {
    "hex": "#207f53",
    "rgb": "rgb(32, 127, 83)",
    "category": "cyan",
    "id": 152
  },
  {
    "hex": "#237e55",
    "rgb": "rgb(35, 126, 85)",
    "category": "cyan",
    "id": 153
  },
  {
    "hex": "#326b52",
    "rgb": "rgb(50, 107, 82)",
    "category": "cyan",
    "id": 154
  },
  {
    "hex": "#2e7457",
    "rgb": "rgb(46, 116, 87)",
    "category": "cyan",
    "id": 155
  },
  {
    "hex": "#2b8360",
    "rgb": "rgb(43, 131, 96)",
    "category": "cyan",
    "id": 156
  },
  {
    "hex": "#397b62",
    "rgb": "rgb(57, 123, 98)",
    "category": "cyan",
    "id": 157
  },
  {
    "hex": "#33bb89",
    "rgb": "rgb(51, 187, 137)",
    "category": "cyan",
    "id": 158
  },
  {
    "hex": "#2e735b",
    "rgb": "rgb(46, 115, 91)",
    "category": "cyan",
    "id": 159
  },
  {
    "hex": "#509f85",
    "rgb": "rgb(80, 159, 133)",
    "category": "cyan",
    "id": 160
  },
  {
    "hex": "#2f705b",
    "rgb": "rgb(47, 112, 91)",
    "category": "cyan",
    "id": 161
  },
  {
    "hex": "#4cb394",
    "rgb": "rgb(76, 179, 148)",
    "category": "cyan",
    "id": 162
  },
  {
    "hex": "#33cba0",
    "rgb": "rgb(51, 203, 160)",
    "category": "cyan",
    "id": 163
  },
  {
    "hex": "#4da48d",
    "rgb": "rgb(77, 164, 141)",
    "category": "cyan",
    "id": 164
  },
  {
    "hex": "#398774",
    "rgb": "rgb(57, 135, 116)",
    "category": "cyan",
    "id": 165
  },
  {
    "hex": "#298e77",
    "rgb": "rgb(41, 142, 119)",
    "category": "cyan",
    "id": 166
  },
  {
    "hex": "#38b499",
    "rgb": "rgb(56, 180, 153)",
    "category": "cyan",
    "id": 167
  },
  {
    "hex": "#35776a",
    "rgb": "rgb(53, 119, 106)",
    "category": "cyan",
    "id": 168
  },
  {
    "hex": "#2b8373",
    "rgb": "rgb(43, 131, 115)",
    "category": "cyan",
    "id": 169
  },
  {
    "hex": "#338376",
    "rgb": "rgb(51, 131, 118)",
    "category": "cyan",
    "id": 170
  },
  {
    "hex": "#4ba295",
    "rgb": "rgb(75, 162, 149)",
    "category": "cyan",
    "id": 171
  },
  {
    "hex": "#41bdac",
    "rgb": "rgb(65, 189, 172)",
    "category": "cyan",
    "id": 172
  },
  {
    "hex": "#46aca0",
    "rgb": "rgb(70, 172, 160)",
    "category": "cyan",
    "id": 173
  },
  {
    "hex": "#357b74",
    "rgb": "rgb(53, 123, 116)",
    "category": "cyan",
    "id": 174
  },
  {
    "hex": "#47a69e",
    "rgb": "rgb(71, 166, 158)",
    "category": "cyan",
    "id": 175
  },
  {
    "hex": "#2fa59d",
    "rgb": "rgb(47, 165, 157)",
    "category": "cyan",
    "id": 176
  },
  {
    "hex": "#2a6f6b",
    "rgb": "rgb(42, 111, 107)",
    "category": "cyan",
    "id": 177
  },
  {
    "hex": "#478c89",
    "rgb": "rgb(71, 140, 137)",
    "category": "cyan",
    "id": 178
  },
  {
    "hex": "#4a8d8c",
    "rgb": "rgb(74, 141, 140)",
    "category": "cyan",
    "id": 179
  },
  {
    "hex": "#257e7e",
    "rgb": "rgb(37, 126, 126)",
    "category": "cyan",
    "id": 180
  },
  {
    "hex": "#398485",
    "rgb": "rgb(57, 132, 133)",
    "category": "cyan",
    "id": 181
  },
  {
    "hex": "#50a7aa",
    "rgb": "rgb(80, 167, 170)",
    "category": "cyan",
    "id": 182
  },
  {
    "hex": "#3f7a7e",
    "rgb": "rgb(63, 122, 126)",
    "category": "cyan",
    "id": 183
  },
  {
    "hex": "#459fa5",
    "rgb": "rgb(69, 159, 165)",
    "category": "cyan",
    "id": 184
  },
  {
    "hex": "#2b99a3",
    "rgb": "rgb(43, 153, 163)",
    "category": "cyan",
    "id": 185
  },
  {
    "hex": "#398f98",
    "rgb": "rgb(57, 143, 152)",
    "category": "cyan",
    "id": 186
  },
  {
    "hex": "#307a84",
    "rgb": "rgb(48, 122, 132)",
    "category": "cyan",
    "id": 187
  },
  {
    "hex": "#2c98a9",
    "rgb": "rgb(44, 152, 169)",
    "category": "cyan",
    "id": 188
  },
  {
    "hex": "#45a0b0",
    "rgb": "rgb(69, 160, 176)",
    "category": "cyan",
    "id": 189
  },
  {
    "hex": "#4a8c99",
    "rgb": "rgb(74, 140, 153)",
    "category": "cyan",
    "id": 190
  },
  {
    "hex": "#3e91a3",
    "rgb": "rgb(62, 145, 163)",
    "category": "cyan",
    "id": 191
  },
  {
    "hex": "#226d80",
    "rgb": "rgb(34, 109, 128)",
    "category": "cyan",
    "id": 192
  },
  {
    "hex": "#32798d",
    "rgb": "rgb(50, 121, 141)",
    "category": "cyan",
    "id": 193
  },
  {
    "hex": "#2c6d81",
    "rgb": "rgb(44, 109, 129)",
    "category": "cyan",
    "id": 194
  },
  {
    "hex": "#3c9cbb",
    "rgb": "rgb(60, 156, 187)",
    "category": "cyan",
    "id": 195
  },
  {
    "hex": "#4e8599",
    "rgb": "rgb(78, 133, 153)",
    "category": "cyan",
    "id": 196
  },
  {
    "hex": "#3d7185",
    "rgb": "rgb(61, 113, 133)",
    "category": "cyan",
    "id": 197
  },
  {
    "hex": "#356275",
    "rgb": "rgb(53, 98, 117)",
    "category": "cyan",
    "id": 198
  },
  {
    "hex": "#4a839e",
    "rgb": "rgb(74, 131, 158)",
    "category": "cyan",
    "id": 199
  },
  {
    "hex": "#3788b0",
    "rgb": "rgb(55, 136, 176)",
    "category": "cyan",
    "id": 200
  },
  {
    "hex": "#27607e",
    "rgb": "rgb(39, 96, 126)",
    "category": "cyan",
    "id": 201
  },
  {
    "hex": "#2d6b8f",
    "rgb": "rgb(45, 107, 143)",
    "category": "cyan",
    "id": 202
  },
  {
    "hex": "#417fa5",
    "rgb": "rgb(65, 127, 165)",
    "category": "cyan",
    "id": 203
  },
  {
    "hex": "#3e7fab",
    "rgb": "rgb(62, 127, 171)",
    "category": "cyan",
    "id": 204
  },
  {
    "hex": "#476d88",
    "rgb": "rgb(71, 109, 136)",
    "category": "cyan",
    "id": 205
  },
  {
    "hex": "#28577b",
    "rgb": "rgb(40, 87, 123)",
    "category": "cyan",
    "id": 206
  },
  {
    "hex": "#356082",
    "rgb": "rgb(53, 96, 130)",
    "category": "cyan",
    "id": 207
  },
  {
    "hex": "#476988",
    "rgb": "rgb(71, 105, 136)",
    "category": "cyan",
    "id": 208
  },
  {
    "hex": "#2b557d",
    "rgb": "rgb(43, 85, 125)",
    "category": "cyan",
    "id": 209
  },
  {
    "hex": "#405f7f",
    "rgb": "rgb(64, 95, 127)",
    "category": "blue",
    "id": 210
  },
  {
    "hex": "#4a75a2",
    "rgb": "rgb(74, 117, 162)",
    "category": "blue",
    "id": 211
  },
  {
    "hex": "#4d729d",
    "rgb": "rgb(77, 114, 157)",
    "category": "blue",
    "id": 212
  },
  {
    "hex": "#466c9a",
    "rgb": "rgb(70, 108, 154)",
    "category": "blue",
    "id": 213
  },
  {
    "hex": "#3774c3",
    "rgb": "rgb(55, 116, 195)",
    "category": "blue",
    "id": 214
  },
  {
    "hex": "#40679e",
    "rgb": "rgb(64, 103, 158)",
    "category": "blue",
    "id": 215
  },
  {
    "hex": "#496fa9",
    "rgb": "rgb(73, 111, 169)",
    "category": "blue",
    "id": 216
  },
  {
    "hex": "#3e5882",
    "rgb": "rgb(62, 88, 130)",
    "category": "blue",
    "id": 217
  },
  {
    "hex": "#3f6dbd",
    "rgb": "rgb(63, 109, 189)",
    "category": "blue",
    "id": 218
  },
  {
    "hex": "#305bac",
    "rgb": "rgb(48, 91, 172)",
    "category": "blue",
    "id": 219
  },
  {
    "hex": "#314876",
    "rgb": "rgb(49, 72, 118)",
    "category": "blue",
    "id": 220
  },
  {
    "hex": "#26417c",
    "rgb": "rgb(38, 65, 124)",
    "category": "blue",
    "id": 221
  },
  {
    "hex": "#4160a9",
    "rgb": "rgb(65, 96, 169)",
    "category": "blue",
    "id": 222
  },
  {
    "hex": "#324470",
    "rgb": "rgb(50, 68, 112)",
    "category": "blue",
    "id": 223
  },
  {
    "hex": "#3252a8",
    "rgb": "rgb(50, 82, 168)",
    "category": "blue",
    "id": 224
  },
  {
    "hex": "#274397",
    "rgb": "rgb(39, 67, 151)",
    "category": "blue",
    "id": 225
  },
  {
    "hex": "#3a4c87",
    "rgb": "rgb(58, 76, 135)",
    "category": "blue",
    "id": 226
  },
  {
    "hex": "#5064ac",
    "rgb": "rgb(80, 100, 172)",
    "category": "blue",
    "id": 227
  },
  {
    "hex": "#455491",
    "rgb": "rgb(69, 84, 145)",
    "category": "blue",
    "id": 228
  },
  {
    "hex": "#394888",
    "rgb": "rgb(57, 72, 136)",
    "category": "blue",
    "id": 229
  },
  {
    "hex": "#2a3983",
    "rgb": "rgb(42, 57, 131)",
    "category": "blue",
    "id": 230
  },
  {
    "hex": "#2a3571",
    "rgb": "rgb(42, 53, 113)",
    "category": "blue",
    "id": 231
  },
  {
    "hex": "#4351af",
    "rgb": "rgb(67, 81, 175)",
    "category": "blue",
    "id": 232
  },
  {
    "hex": "#535c9b",
    "rgb": "rgb(83, 92, 155)",
    "category": "blue",
    "id": 233
  },
  {
    "hex": "#263084",
    "rgb": "rgb(38, 48, 132)",
    "category": "blue",
    "id": 234
  },
  {
    "hex": "#434989",
    "rgb": "rgb(67, 73, 137)",
    "category": "blue",
    "id": 235
  },
  {
    "hex": "#2c3170",
    "rgb": "rgb(44, 49, 112)",
    "category": "blue",
    "id": 236
  },
  {
    "hex": "#3338a7",
    "rgb": "rgb(51, 56, 167)",
    "category": "blue",
    "id": 237
  },
  {
    "hex": "#343895",
    "rgb": "rgb(52, 56, 149)",
    "category": "blue",
    "id": 238
  },
  {
    "hex": "#38396f",
    "rgb": "rgb(56, 57, 111)",
    "category": "blue",
    "id": 239
  },
  {
    "hex": "#3f3f7f",
    "rgb": "rgb(63, 63, 127)",
    "category": "blue",
    "id": 240
  },
  {
    "hex": "#3a38a9",
    "rgb": "rgb(58, 56, 169)",
    "category": "blue",
    "id": 241
  },
  {
    "hex": "#4844ad",
    "rgb": "rgb(72, 68, 173)",
    "category": "blue",
    "id": 242
  },
  {
    "hex": "#373473",
    "rgb": "rgb(55, 52, 115)",
    "category": "blue",
    "id": 243
  },
  {
    "hex": "#3f37b0",
    "rgb": "rgb(63, 55, 176)",
    "category": "blue",
    "id": 244
  },
  {
    "hex": "#473cbc",
    "rgb": "rgb(71, 60, 188)",
    "category": "blue",
    "id": 245
  },
  {
    "hex": "#2b227b",
    "rgb": "rgb(43, 34, 123)",
    "category": "blue",
    "id": 246
  },
  {
    "hex": "#4033aa",
    "rgb": "rgb(64, 51, 170)",
    "category": "blue",
    "id": 247
  },
  {
    "hex": "#3a2d94",
    "rgb": "rgb(58, 45, 148)",
    "category": "blue",
    "id": 248
  },
  {
    "hex": "#5444b0",
    "rgb": "rgb(84, 68, 176)",
    "category": "blue",
    "id": 249
  },
  {
    "hex": "#5849a5",
    "rgb": "rgb(88, 73, 165)",
    "category": "blue",
    "id": 250
  },
  {
    "hex": "#413283",
    "rgb": "rgb(65, 50, 131)",
    "category": "blue",
    "id": 251
  },
  {
    "hex": "#47397f",
    "rgb": "rgb(71, 57, 127)",
    "category": "blue",
    "id": 252
  },
  {
    "hex": "#463b71",
    "rgb": "rgb(70, 59, 113)",
    "category": "blue",
    "id": 253
  },
  {
    "hex": "#432c8d",
    "rgb": "rgb(67, 44, 141)",
    "category": "blue",
    "id": 254
  },
  {
    "hex": "#402f74",
    "rgb": "rgb(64, 47, 116)",
    "category": "blue",
    "id": 255
  },
  {
    "hex": "#3c2185",
    "rgb": "rgb(60, 33, 133)",
    "category": "blue",
    "id": 256
  },
  {
    "hex": "#423367",
    "rgb": "rgb(66, 51, 103)",
    "category": "blue",
    "id": 257
  },
  {
    "hex": "#6641bd",
    "rgb": "rgb(102, 65, 189)",
    "category": "blue",
    "id": 258
  },
  {
    "hex": "#684da1",
    "rgb": "rgb(104, 77, 161)",
    "category": "blue",
    "id": 259
  },
  {
    "hex": "#5b34a9",
    "rgb": "rgb(91, 52, 169)",
    "category": "blue",
    "id": 260
  },
  {
    "hex": "#5d3b9c",
    "rgb": "rgb(93, 59, 156)",
    "category": "blue",
    "id": 261
  },
  {
    "hex": "#6338ad",
    "rgb": "rgb(99, 56, 173)",
    "category": "blue",
    "id": 262
  },
  {
    "hex": "#5f30aa",
    "rgb": "rgb(95, 48, 170)",
    "category": "blue",
    "id": 263
  },
  {
    "hex": "#5d3895",
    "rgb": "rgb(93, 56, 149)",
    "category": "blue",
    "id": 264
  },
  {
    "hex": "#503675",
    "rgb": "rgb(80, 54, 117)",
    "category": "blue",
    "id": 265
  },
  {
    "hex": "#6e48a0",
    "rgb": "rgb(110, 72, 160)",
    "category": "blue",
    "id": 266
  },
  {
    "hex": "#522489",
    "rgb": "rgb(82, 36, 137)",
    "category": "blue",
    "id": 267
  },
  {
    "hex": "#4c306c",
    "rgb": "rgb(76, 48, 108)",
    "category": "blue",
    "id": 268
  },
  {
    "hex": "#5d338a",
    "rgb": "rgb(93, 51, 138)",
    "category": "blue",
    "id": 269
  },
  {
    "hex": "#7b3eb7",
    "rgb": "rgb(123, 62, 183)",
    "category": "purple",
    "id": 270
  },
  {
    "hex": "#813dc1",
    "rgb": "rgb(129, 61, 193)",
    "category": "purple",
    "id": 271
  },
  {
    "hex": "#7f34c0",
    "rgb": "rgb(127, 52, 192)",
    "category": "purple",
    "id": 272
  },
  {
    "hex": "#5c2c84",
    "rgb": "rgb(92, 44, 132)",
    "category": "purple",
    "id": 273
  },
  {
    "hex": "#613781",
    "rgb": "rgb(97, 55, 129)",
    "category": "purple",
    "id": 274
  },
  {
    "hex": "#792eae",
    "rgb": "rgb(121, 46, 174)",
    "category": "purple",
    "id": 275
  },
  {
    "hex": "#5f2a82",
    "rgb": "rgb(95, 42, 130)",
    "category": "purple",
    "id": 276
  },
  {
    "hex": "#713298",
    "rgb": "rgb(113, 50, 152)",
    "category": "purple",
    "id": 277
  },
  {
    "hex": "#723695",
    "rgb": "rgb(114, 54, 149)",
    "category": "purple",
    "id": 278
  },
  {
    "hex": "#5d287a",
    "rgb": "rgb(93, 40, 122)",
    "category": "purple",
    "id": 279
  },
  {
    "hex": "#5c396d",
    "rgb": "rgb(92, 57, 109)",
    "category": "purple",
    "id": 280
  },
  {
    "hex": "#773497",
    "rgb": "rgb(119, 52, 151)",
    "category": "purple",
    "id": 281
  },
  {
    "hex": "#672285",
    "rgb": "rgb(103, 34, 133)",
    "category": "purple",
    "id": 282
  },
  {
    "hex": "#66267f",
    "rgb": "rgb(102, 38, 127)",
    "category": "purple",
    "id": 283
  },
  {
    "hex": "#783d8d",
    "rgb": "rgb(120, 61, 141)",
    "category": "purple",
    "id": 284
  },
  {
    "hex": "#7e3c94",
    "rgb": "rgb(126, 60, 148)",
    "category": "purple",
    "id": 285
  },
  {
    "hex": "#7e3e92",
    "rgb": "rgb(126, 62, 146)",
    "category": "purple",
    "id": 286
  },
  {
    "hex": "#913fa8",
    "rgb": "rgb(145, 63, 168)",
    "category": "purple",
    "id": 287
  },
  {
    "hex": "#a340bc",
    "rgb": "rgb(163, 64, 188)",
    "category": "purple",
    "id": 288
  },
  {
    "hex": "#78248a",
    "rgb": "rgb(120, 36, 138)",
    "category": "purple",
    "id": 289
  },
  {
    "hex": "#7c4686",
    "rgb": "rgb(124, 70, 134)",
    "category": "purple",
    "id": 290
  },
  {
    "hex": "#6f2c7b",
    "rgb": "rgb(111, 44, 123)",
    "category": "purple",
    "id": 291
  },
  {
    "hex": "#903b9d",
    "rgb": "rgb(144, 59, 157)",
    "category": "purple",
    "id": 292
  },
  {
    "hex": "#6f2a79",
    "rgb": "rgb(111, 42, 121)",
    "category": "purple",
    "id": 293
  },
  {
    "hex": "#6b2a72",
    "rgb": "rgb(107, 42, 114)",
    "category": "purple",
    "id": 294
  },
  {
    "hex": "#9b4fa2",
    "rgb": "rgb(155, 79, 162)",
    "category": "purple",
    "id": 295
  },
  {
    "hex": "#8b2f92",
    "rgb": "rgb(139, 47, 146)",
    "category": "purple",
    "id": 296
  },
  {
    "hex": "#87368b",
    "rgb": "rgb(135, 54, 139)",
    "category": "purple",
    "id": 297
  },
  {
    "hex": "#974d9a",
    "rgb": "rgb(151, 77, 154)",
    "category": "purple",
    "id": 298
  },
  {
    "hex": "#832384",
    "rgb": "rgb(131, 35, 132)",
    "category": "purple",
    "id": 299
  },
  {
    "hex": "#b642b6",
    "rgb": "rgb(182, 66, 182)",
    "category": "purple",
    "id": 300
  },
  {
    "hex": "#712a70",
    "rgb": "rgb(113, 42, 112)",
    "category": "purple",
    "id": 301
  },
  {
    "hex": "#a941a6",
    "rgb": "rgb(169, 65, 166)",
    "category": "purple",
    "id": 302
  },
  {
    "hex": "#843180",
    "rgb": "rgb(132, 49, 128)",
    "category": "purple",
    "id": 303
  },
  {
    "hex": "#9d4597",
    "rgb": "rgb(157, 69, 151)",
    "category": "purple",
    "id": 304
  },
  {
    "hex": "#832c7b",
    "rgb": "rgb(131, 44, 123)",
    "category": "purple",
    "id": 305
  },
  {
    "hex": "#8b3782",
    "rgb": "rgb(139, 55, 130)",
    "category": "purple",
    "id": 306
  },
  {
    "hex": "#a15598",
    "rgb": "rgb(161, 85, 152)",
    "category": "purple",
    "id": 307
  },
  {
    "hex": "#a74a9a",
    "rgb": "rgb(167, 74, 154)",
    "category": "purple",
    "id": 308
  },
  {
    "hex": "#742768",
    "rgb": "rgb(116, 39, 104)",
    "category": "purple",
    "id": 309
  },
  {
    "hex": "#a23c91",
    "rgb": "rgb(162, 60, 145)",
    "category": "purple",
    "id": 310
  },
  {
    "hex": "#8d3b7e",
    "rgb": "rgb(141, 59, 126)",
    "category": "purple",
    "id": 311
  },
  {
    "hex": "#713565",
    "rgb": "rgb(113, 53, 101)",
    "category": "purple",
    "id": 312
  },
  {
    "hex": "#9c3c87",
    "rgb": "rgb(156, 60, 135)",
    "category": "purple",
    "id": 313
  },
  {
    "hex": "#782765",
    "rgb": "rgb(120, 39, 101)",
    "category": "purple",
    "id": 314
  },
  {
    "hex": "#813b70",
    "rgb": "rgb(129, 59, 112)",
    "category": "purple",
    "id": 315
  },
  {
    "hex": "#ab368c",
    "rgb": "rgb(171, 54, 140)",
    "category": "purple",
    "id": 316
  },
  {
    "hex": "#ad348b",
    "rgb": "rgb(173, 52, 139)",
    "category": "purple",
    "id": 317
  },
  {
    "hex": "#b74494",
    "rgb": "rgb(183, 68, 148)",
    "category": "purple",
    "id": 318
  },
  {
    "hex": "#922971",
    "rgb": "rgb(146, 41, 113)",
    "category": "purple",
    "id": 319
  },
  {
    "hex": "#6a3358",
    "rgb": "rgb(106, 51, 88)",
    "category": "purple",
    "id": 320
  },
  {
    "hex": "#8a2466",
    "rgb": "rgb(138, 36, 102)",
    "category": "purple",
    "id": 321
  },
  {
    "hex": "#8e316c",
    "rgb": "rgb(142, 49, 108)",
    "category": "purple",
    "id": 322
  },
  {
    "hex": "#7e3462",
    "rgb": "rgb(126, 52, 98)",
    "category": "purple",
    "id": 323
  },
  {
    "hex": "#8e4b73",
    "rgb": "rgb(142, 75, 115)",
    "category": "purple",
    "id": 324
  },
  {
    "hex": "#9b3370",
    "rgb": "rgb(155, 51, 112)",
    "category": "purple",
    "id": 325
  },
  {
    "hex": "#732d54",
    "rgb": "rgb(115, 45, 84)",
    "category": "purple",
    "id": 326
  },
  {
    "hex": "#7a3a5d",
    "rgb": "rgb(122, 58, 93)",
    "category": "purple",
    "id": 327
  },
  {
    "hex": "#8c3262",
    "rgb": "rgb(140, 50, 98)",
    "category": "purple",
    "id": 328
  },
  {
    "hex": "#ab5280",
    "rgb": "rgb(171, 82, 128)",
    "category": "purple",
    "id": 329
  },
  {
    "hex": "#973c6a",
    "rgb": "rgb(151, 60, 106)",
    "category": "red",
    "id": 330
  },
  {
    "hex": "#6c334f",
    "rgb": "rgb(108, 51, 79)",
    "category": "red",
    "id": 331
  },
  {
    "hex": "#7e2c52",
    "rgb": "rgb(126, 44, 82)",
    "category": "red",
    "id": 332
  },
  {
    "hex": "#913860",
    "rgb": "rgb(145, 56, 96)",
    "category": "red",
    "id": 333
  },
  {
    "hex": "#a73e6b",
    "rgb": "rgb(167, 62, 107)",
    "category": "red",
    "id": 334
  },
  {
    "hex": "#6d374d",
    "rgb": "rgb(109, 55, 77)",
    "category": "red",
    "id": 335
  },
  {
    "hex": "#86284e",
    "rgb": "rgb(134, 40, 78)",
    "category": "red",
    "id": 336
  },
  {
    "hex": "#81445b",
    "rgb": "rgb(129, 68, 91)",
    "category": "red",
    "id": 337
  },
  {
    "hex": "#b63967",
    "rgb": "rgb(182, 57, 103)",
    "category": "red",
    "id": 338
  },
  {
    "hex": "#8e3755",
    "rgb": "rgb(142, 55, 85)",
    "category": "red",
    "id": 339
  },
  {
    "hex": "#7a3b50",
    "rgb": "rgb(122, 59, 80)",
    "category": "red",
    "id": 340
  },
  {
    "hex": "#8b2d4b",
    "rgb": "rgb(139, 45, 75)",
    "category": "red",
    "id": 341
  },
  {
    "hex": "#95405a",
    "rgb": "rgb(149, 64, 90)",
    "category": "red",
    "id": 342
  },
  {
    "hex": "#a94461",
    "rgb": "rgb(169, 68, 97)",
    "category": "red",
    "id": 343
  },
  {
    "hex": "#86233e",
    "rgb": "rgb(134, 35, 62)",
    "category": "red",
    "id": 344
  },
  {
    "hex": "#683340",
    "rgb": "rgb(104, 51, 64)",
    "category": "red",
    "id": 345
  },
  {
    "hex": "#6a323f",
    "rgb": "rgb(106, 50, 63)",
    "category": "red",
    "id": 346
  },
  {
    "hex": "#6d313e",
    "rgb": "rgb(109, 49, 62)",
    "category": "red",
    "id": 347
  },
  {
    "hex": "#a55162",
    "rgb": "rgb(165, 81, 98)",
    "category": "red",
    "id": 348
  },
  {
    "hex": "#964251",
    "rgb": "rgb(150, 66, 81)",
    "category": "red",
    "id": 349
  },
  {
    "hex": "#a94455",
    "rgb": "rgb(169, 68, 85)",
    "category": "red",
    "id": 350
  },
  {
    "hex": "#7f2734",
    "rgb": "rgb(127, 39, 52)",
    "category": "red",
    "id": 351
  },
  {
    "hex": "#b14453",
    "rgb": "rgb(177, 68, 83)",
    "category": "red",
    "id": 352
  },
  {
    "hex": "#b63e4c",
    "rgb": "rgb(182, 62, 76)",
    "category": "red",
    "id": 353
  },
  {
    "hex": "#88363e",
    "rgb": "rgb(136, 54, 62)",
    "category": "red",
    "id": 354
  },
  {
    "hex": "#9c444c",
    "rgb": "rgb(156, 68, 76)",
    "category": "red",
    "id": 355
  },
  {
    "hex": "#742f33",
    "rgb": "rgb(116, 47, 51)",
    "category": "red",
    "id": 356
  },
  {
    "hex": "#7d292d",
    "rgb": "rgb(125, 41, 45)",
    "category": "red",
    "id": 357
  },
  {
    "hex": "#893c3e",
    "rgb": "rgb(137, 60, 62)",
    "category": "red",
    "id": 358
  },
  {
    "hex": "#994a4b",
    "rgb": "rgb(153, 74, 75)",
    "category": "red",
    "id": 359
  },
  {
    "hex": "#962a2a",
    "rgb": "rgb(150, 42, 42)",
    "category": "red",
    "id": 360
  }
]