[
  {
    "hex": "#dc9291",
    "rgb": "rgb(220, 146, 145)",
    "category": "red",
    "id": 1
  },
  {
    "hex": "#f5d4d3",
    "rgb": "rgb(245, 212, 211)",
    "category": "red",
    "id": 2
  },
  {
    "hex": "#e1a3a0",
    "rgb": "rgb(225, 163, 160)",
    "category": "red",
    "id": 3
  },
  {
    "hex": "#f4c4c0",
    "rgb": "rgb(244, 196, 192)",
    "category": "red",
    "id": 4
  },
  {
    "hex": "#efc2be",
    "rgb": "rgb(239, 194, 190)",
    "category": "red",
    "id": 5
  },
  {
    "hex": "#e89a91",
    "rgb": "rgb(232, 154, 145)",
    "category": "red",
    "id": 6
  },
  {
    "hex": "#f5d1cc",
    "rgb": "rgb(245, 209, 204)",
    "category": "red",
    "id": 7
  },
  {
    "hex": "#f2bfb7",
    "rgb": "rgb(242, 191, 183)",
    "category": "red",
    "id": 8
  },
  {
    "hex": "#eac0b9",
    "rgb": "rgb(234, 192, 185)",
    "category": "red",
    "id": 9
  },
  {
    "hex": "#e5b8af",
    "rgb": "rgb(229, 184, 175)",
    "category": "red",
    "id": 10
  },
  {
    "hex": "#e7b3a7",
    "rgb": "rgb(231, 179, 167)",
    "category": "red",
    "id": 11
  },
  {
    "hex": "#f3cfc6",
    "rgb": "rgb(243, 207, 198)",
    "category": "red",
    "id": 12
  },
  {
    "hex": "#f1d7d0",
    "rgb": "rgb(241, 215, 208)",
    "category": "red",
    "id": 13
  },
  {
    "hex": "#f2d7cf",
    "rgb": "rgb(242, 215, 207)",
    "category": "red",
    "id": 14
  },
  {
    "hex": "#e9baaa",
    "rgb": "rgb(233, 186, 170)",
    "category": "red",
    "id": 15
  },
  {
    "hex": "#f5d9cf",
    "rgb": "rgb(245, 217, 207)",
    "category": "red",
    "id": 16
  },
  {
    "hex": "#e6ae97",
    "rgb": "rgb(230, 174, 151)",
    "category": "red",
    "id": 17
  },
  {
    "hex": "#dda68f",
    "rgb": "rgb(221, 166, 143)",
    "category": "red",
    "id": 18
  },
  {
    "hex": "#ebc4b2",
    "rgb": "rgb(235, 196, 178)",
    "category": "red",
    "id": 19
  },
  {
    "hex": "#e6a483",
    "rgb": "rgb(230, 164, 131)",
    "category": "red",
    "id": 20
  },
  {
    "hex": "#eebda3",
    "rgb": "rgb(238, 189, 163)",
    "category": "red",
    "id": 21
  },
  {
    "hex": "#e7b89d",
    "rgb": "rgb(231, 184, 157)",
    "category": "red",
    "id": 22
  },
  {
    "hex": "#e3b69a",
    "rgb": "rgb(227, 182, 154)",
    "category": "red",
    "id": 23
  },
  {
    "hex": "#eacdba",
    "rgb": "rgb(234, 205, 186)",
    "category": "red",
    "id": 24
  },
  {
    "hex": "#ecd6c7",
    "rgb": "rgb(236, 214, 199)",
    "category": "red",
    "id": 25
  },
  {
    "hex": "#eac1a2",
    "rgb": "rgb(234, 193, 162)",
    "category": "red",
    "id": 26
  },
  {
    "hex": "#deb593",
    "rgb": "rgb(222, 181, 147)",
    "category": "red",
    "id": 27
  },
  {
    "hex": "#e3c5ab",
    "rgb": "rgb(227, 197, 171)",
    "category": "red",
    "id": 28
  },
  {
    "hex": "#eacbae",
    "rgb": "rgb(234, 203, 174)",
    "category": "red",
    "id": 29
  },
  {
    "hex": "#f0d7bd",
    "rgb": "rgb(240, 215, 189)",
    "category": "yellow",
    "id": 30
  },
  {
    "hex": "#f0d8bf",
    "rgb": "rgb(240, 216, 191)",
    "category": "yellow",
    "id": 31
  },
  {
    "hex": "#f5e5d3",
    "rgb": "rgb(245, 229, 211)",
    "category": "yellow",
    "id": 32
  },
  {
    "hex": "#e0c39f",
    "rgb": "rgb(224, 195, 159)",
    "category": "yellow",
    "id": 33
  },
  {
    "hex": "#e5c395",
    "rgb": "rgb(229, 195, 149)",
    "category": "yellow",
    "id": 34
  },
  {
    "hex": "#ead0ab",
    "rgb": "rgb(234, 208, 171)",
    "category": "yellow",
    "id": 35
  },
  {
    "hex": "#ecd7b7",
    "rgb": "rgb(236, 215, 183)",
    "category": "yellow",
    "id": 36
  },
  {
    "hex": "#e7cda3",
    "rgb": "rgb(231, 205, 163)",
    "category": "yellow",
    "id": 37
  },
  {
    "hex": "#e5c99a",
    "rgb": "rgb(229, 201, 154)",
    "category": "yellow",
    "id": 38
  },
  {
    "hex": "#e1cba2",
    "rgb": "rgb(225, 203, 162)",
    "category": "yellow",
    "id": 39
  },
  {
    "hex": "#e9d9b9",
    "rgb": "rgb(233, 217, 185)",
    "category": "yellow",
    "id": 40
  },
  {
    "hex": "#e8ce95",
    "rgb": "rgb(232, 206, 149)",
    "category": "yellow",
    "id": 41
  },
  {
    "hex": "#e7cc8f",
    "rgb": "rgb(231, 204, 143)",
    "category": "yellow",
    "id": 42
  },
  {
    "hex": "#e5d19f",
    "rgb": "rgb(229, 209, 159)",
    "category": "yellow",
    "id": 43
  },
  {
    "hex": "#e0ce9c",
    "rgb": "rgb(224, 206, 156)",
    "category": "yellow",
    "id": 44
  },
  {
    "hex": "#ede0ba",
    "rgb": "rgb(237, 224, 186)",
    "category": "yellow",
    "id": 45
  },
  {
    "hex": "#eddead",
    "rgb": "rgb(237, 222, 173)",
    "category": "yellow",
    "id": 46
  },
  {
    "hex": "#eedd9f",
    "rgb": "rgb(238, 221, 159)",
    "category": "yellow",
    "id": 47
  },
  {
    "hex": "#e3d59c",
    "rgb": "rgb(227, 213, 156)",
    "category": "yellow",
    "id": 48
  },
  {
    "hex": "#f0e6ba",
    "rgb": "rgb(240, 230, 186)",
    "category": "yellow",
    "id": 49
  },
  {
    "hex": "#f1ebc8",
    "rgb": "rgb(241, 235, 200)",
    "category": "yellow",
    "id": 50
  },
  {
    "hex": "#ece19e",
    "rgb": "rgb(236, 225, 158)",
    "category": "yellow",
    "id": 51
  },
  {
    "hex": "#f1ebc8",
    "rgb": "rgb(241, 235, 200)",
    "category": "yellow",
    "id": 52
  },
  {
    "hex": "#f6f1cf",
    "rgb": "rgb(246, 241, 207)",
    "category": "yellow",
    "id": 53
  },
  {
    "hex": "#f3efcb",
    "rgb": "rgb(243, 239, 203)",
    "category": "yellow",
    "id": 54
  },
  {
    "hex": "#f4f0ce",
    "rgb": "rgb(244, 240, 206)",
    "category": "yellow",
    "id": 55
  },
  {
    "hex": "#e5e0a7",
    "rgb": "rgb(229, 224, 167)",
    "category": "yellow",
    "id": 56
  },
  {
    "hex": "#ddda98",
    "rgb": "rgb(221, 218, 152)",
    "category": "yellow",
    "id": 57
  },
  {
    "hex": "#f2f1d1",
    "rgb": "rgb(242, 241, 209)",
    "category": "yellow",
    "id": 58
  },
  {
    "hex": "#f5f4d3",
    "rgb": "rgb(245, 244, 211)",
    "category": "yellow",
    "id": 59
  },
  {
    "hex": "#e7e7a5",
    "rgb": "rgb(231, 231, 165)",
    "category": "yellow",
    "id": 60
  },
  {
    "hex": "#e2e483",
    "rgb": "rgb(226, 228, 131)",
    "category": "yellow",
    "id": 61
  },
  {
    "hex": "#f4f5d0",
    "rgb": "rgb(244, 245, 208)",
    "category": "yellow",
    "id": 62
  },
  {
    "hex": "#e3e6b4",
    "rgb": "rgb(227, 230, 180)",
    "category": "yellow",
    "id": 63
  },
  {
    "hex": "#e3e989",
    "rgb": "rgb(227, 233, 137)",
    "category": "yellow",
    "id": 64
  },
  {
    "hex": "#e1e98a",
    "rgb": "rgb(225, 233, 138)",
    "category": "yellow",
    "id": 65
  },
  {
    "hex": "#dde3a2",
    "rgb": "rgb(221, 227, 162)",
    "category": "yellow",
    "id": 66
  },
  {
    "hex": "#eff3d4",
    "rgb": "rgb(239, 243, 212)",
    "category": "yellow",
    "id": 67
  },
  {
    "hex": "#f2f7d1",
    "rgb": "rgb(242, 247, 209)",
    "category": "yellow",
    "id": 68
  },
  {
    "hex": "#e5f0aa",
    "rgb": "rgb(229, 240, 170)",
    "category": "yellow",
    "id": 69
  },
  {
    "hex": "#e7edc8",
    "rgb": "rgb(231, 237, 200)",
    "category": "yellow",
    "id": 70
  },
  {
    "hex": "#dbe5ac",
    "rgb": "rgb(219, 229, 172)",
    "category": "yellow",
    "id": 71
  },
  {
    "hex": "#d7e992",
    "rgb": "rgb(215, 233, 146)",
    "category": "yellow",
    "id": 72
  },
  {
    "hex": "#d6e796",
    "rgb": "rgb(214, 231, 150)",
    "category": "yellow",
    "id": 73
  },
  {
    "hex": "#e3efbd",
    "rgb": "rgb(227, 239, 189)",
    "category": "yellow",
    "id": 74
  },
  {
    "hex": "#d7ea9f",
    "rgb": "rgb(215, 234, 159)",
    "category": "yellow",
    "id": 75
  },
  {
    "hex": "#e8f2ca",
    "rgb": "rgb(232, 242, 202)",
    "category": "yellow",
    "id": 76
  },
  {
    "hex": "#ebf6ce",
    "rgb": "rgb(235, 246, 206)",
    "category": "yellow",
    "id": 77
  },
  {
    "hex": "#dfeebc",
    "rgb": "rgb(223, 238, 188)",
    "category": "yellow",
    "id": 78
  },
  {
    "hex": "#d3ed9c",
    "rgb": "rgb(211, 237, 156)",
    "category": "yellow",
    "id": 79
  },
  {
    "hex": "#d1e8a2",
    "rgb": "rgb(209, 232, 162)",
    "category": "yellow",
    "id": 80
  },
  {
    "hex": "#c8e199",
    "rgb": "rgb(200, 225, 153)",
    "category": "yellow",
    "id": 81
  },
  {
    "hex": "#daebbc",
    "rgb": "rgb(218, 235, 188)",
    "category": "yellow",
    "id": 82
  },
  {
    "hex": "#c5e592",
    "rgb": "rgb(197, 229, 146)",
    "category": "yellow",
    "id": 83
  },
  {
    "hex": "#cce6a5",
    "rgb": "rgb(204, 230, 165)",
    "category": "yellow",
    "id": 84
  },
  {
    "hex": "#bce485",
    "rgb": "rgb(188, 228, 133)",
    "category": "yellow",
    "id": 85
  },
  {
    "hex": "#c7e79d",
    "rgb": "rgb(199, 231, 157)",
    "category": "yellow",
    "id": 86
  },
  {
    "hex": "#bbe28c",
    "rgb": "rgb(187, 226, 140)",
    "category": "yellow",
    "id": 87
  },
  {
    "hex": "#cceaa9",
    "rgb": "rgb(204, 234, 169)",
    "category": "yellow",
    "id": 88
  },
  {
    "hex": "#d6eac0",
    "rgb": "rgb(214, 234, 192)",
    "category": "yellow",
    "id": 89
  },
  {
    "hex": "#e4f6d2",
    "rgb": "rgb(228, 246, 210)",
    "category": "green",
    "id": 90
  },
  {
    "hex": "#c4e6a3",
    "rgb": "rgb(196, 230, 163)",
    "category": "green",
    "id": 91
  },
  {
    "hex": "#d0efb5",
    "rgb": "rgb(208, 239, 181)",
    "category": "green",
    "id": 92
  },
  {
    "hex": "#def4cd",
    "rgb": "rgb(222, 244, 205)",
    "category": "green",
    "id": 93
  },
  {
    "hex": "#c0e9a0",
    "rgb": "rgb(192, 233, 160)",
    "category": "green",
    "id": 94
  },
  {
    "hex": "#cae7b5",
    "rgb": "rgb(202, 231, 181)",
    "category": "green",
    "id": 95
  },
  {
    "hex": "#c5efaa",
    "rgb": "rgb(197, 239, 170)",
    "category": "green",
    "id": 96
  },
  {
    "hex": "#def2d2",
    "rgb": "rgb(222, 242, 210)",
    "category": "green",
    "id": 97
  },
  {
    "hex": "#b6df9e",
    "rgb": "rgb(182, 223, 158)",
    "category": "green",
    "id": 98
  },
  {
    "hex": "#d5eec8",
    "rgb": "rgb(213, 238, 200)",
    "category": "green",
    "id": 99
  },
  {
    "hex": "#bee8a9",
    "rgb": "rgb(190, 232, 169)",
    "category": "green",
    "id": 100
  },
  {
    "hex": "#d0eec2",
    "rgb": "rgb(208, 238, 194)",
    "category": "green",
    "id": 101
  },
  {
    "hex": "#daf5ce",
    "rgb": "rgb(218, 245, 206)",
    "category": "green",
    "id": 102
  },
  {
    "hex": "#dbf3d2",
    "rgb": "rgb(219, 243, 210)",
    "category": "green",
    "id": 103
  },
  {
    "hex": "#a4e58d",
    "rgb": "rgb(164, 229, 141)",
    "category": "green",
    "id": 104
  },
  {
    "hex": "#9de585",
    "rgb": "rgb(157, 229, 133)",
    "category": "green",
    "id": 105
  },
  {
    "hex": "#a5e193",
    "rgb": "rgb(165, 225, 147)",
    "category": "green",
    "id": 106
  },
  {
    "hex": "#bceab0",
    "rgb": "rgb(188, 234, 176)",
    "category": "green",
    "id": 107
  },
  {
    "hex": "#aee6a0",
    "rgb": "rgb(174, 230, 160)",
    "category": "green",
    "id": 108
  },
  {
    "hex": "#cef1c6",
    "rgb": "rgb(206, 241, 198)",
    "category": "green",
    "id": 109
  },
  {
    "hex": "#d3f1cd",
    "rgb": "rgb(211, 241, 205)",
    "category": "green",
    "id": 110
  },
  {
    "hex": "#b2e7a9",
    "rgb": "rgb(178, 231, 169)",
    "category": "green",
    "id": 111
  },
  {
    "hex": "#d3f4ce",
    "rgb": "rgb(211, 244, 206)",
    "category": "green",
    "id": 112
  },
  {
    "hex": "#d2f1cd",
    "rgb": "rgb(210, 241, 205)",
    "category": "green",
    "id": 113
  },
  {
    "hex": "#92e888",
    "rgb": "rgb(146, 232, 136)",
    "category": "green",
    "id": 114
  },
  {
    "hex": "#a7e7a1",
    "rgb": "rgb(167, 231, 161)",
    "category": "green",
    "id": 115
  },
  {
    "hex": "#a3e69e",
    "rgb": "rgb(163, 230, 158)",
    "category": "green",
    "id": 116
  },
  {
    "hex": "#a1e39d",
    "rgb": "rgb(161, 227, 157)",
    "category": "green",
    "id": 117
  },
  {
    "hex": "#b0ebae",
    "rgb": "rgb(176, 235, 174)",
    "category": "green",
    "id": 118
  },
  {
    "hex": "#a1e6a0",
    "rgb": "rgb(161, 230, 160)",
    "category": "green",
    "id": 119
  },
  {
    "hex": "#96e096",
    "rgb": "rgb(150, 224, 150)",
    "category": "green",
    "id": 120
  },
  {
    "hex": "#d3f1d4",
    "rgb": "rgb(211, 241, 212)",
    "category": "green",
    "id": 121
  },
  {
    "hex": "#9ce19e",
    "rgb": "rgb(156, 225, 158)",
    "category": "green",
    "id": 122
  },
  {
    "hex": "#8ddd91",
    "rgb": "rgb(141, 221, 145)",
    "category": "green",
    "id": 123
  },
  {
    "hex": "#ccf0ce",
    "rgb": "rgb(204, 240, 206)",
    "category": "green",
    "id": 124
  },
  {
    "hex": "#c3f4c7",
    "rgb": "rgb(195, 244, 199)",
    "category": "green",
    "id": 125
  },
  {
    "hex": "#8ce995",
    "rgb": "rgb(140, 233, 149)",
    "category": "green",
    "id": 126
  },
  {
    "hex": "#96e69f",
    "rgb": "rgb(150, 230, 159)",
    "category": "green",
    "id": 127
  },
  {
    "hex": "#b0e7b7",
    "rgb": "rgb(176, 231, 183)",
    "category": "green",
    "id": 128
  },
  {
    "hex": "#c3ecc9",
    "rgb": "rgb(195, 236, 201)",
    "category": "green",
    "id": 129
  },
  {
    "hex": "#96e8a3",
    "rgb": "rgb(150, 232, 163)",
    "category": "green",
    "id": 130
  },
  {
    "hex": "#c6f4ce",
    "rgb": "rgb(198, 244, 206)",
    "category": "green",
    "id": 131
  },
  {
    "hex": "#8fe4a0",
    "rgb": "rgb(143, 228, 160)",
    "category": "green",
    "id": 132
  },
  {
    "hex": "#a2e5b1",
    "rgb": "rgb(162, 229, 177)",
    "category": "green",
    "id": 133
  },
  {
    "hex": "#a0e3b0",
    "rgb": "rgb(160, 227, 176)",
    "category": "green",
    "id": 134
  },
  {
    "hex": "#8ddca1",
    "rgb": "rgb(141, 220, 161)",
    "category": "green",
    "id": 135
  },
  {
    "hex": "#b8e8c5",
    "rgb": "rgb(184, 232, 197)",
    "category": "green",
    "id": 136
  },
  {
    "hex": "#afe7bf",
    "rgb": "rgb(175, 231, 191)",
    "category": "green",
    "id": 137
  },
  {
    "hex": "#aee7bf",
    "rgb": "rgb(174, 231, 191)",
    "category": "green",
    "id": 138
  },
  {
    "hex": "#a7edbd",
    "rgb": "rgb(167, 237, 189)",
    "category": "green",
    "id": 139
  },
  {
    "hex": "#c0eecf",
    "rgb": "rgb(192, 238, 207)",
    "category": "green",
    "id": 140
  },
  {
    "hex": "#88e9aa",
    "rgb": "rgb(136, 233, 170)",
    "category": "green",
    "id": 141
  },
  {
    "hex": "#d5f1df",
    "rgb": "rgb(213, 241, 223)",
    "category": "green",
    "id": 142
  },
  {
    "hex": "#b3eeca",
    "rgb": "rgb(179, 238, 202)",
    "category": "green",
    "id": 143
  },
  {
    "hex": "#8fdeaf",
    "rgb": "rgb(143, 222, 175)",
    "category": "green",
    "id": 144
  },
  {
    "hex": "#cbf1db",
    "rgb": "rgb(203, 241, 219)",
    "category": "green",
    "id": 145
  },
  {
    "hex": "#93deb4",
    "rgb": "rgb(147, 222, 180)",
    "category": "green",
    "id": 146
  },
  {
    "hex": "#b7ebce",
    "rgb": "rgb(183, 235, 206)",
    "category": "green",
    "id": 147
  },
  {
    "hex": "#aceecb",
    "rgb": "rgb(172, 238, 203)",
    "category": "green",
    "id": 148
  },
  {
    "hex": "#9fe8c2",
    "rgb": "rgb(159, 232, 194)",
    "category": "green",
    "id": 149
  },
  {
    "hex": "#d4f4e4",
    "rgb": "rgb(212, 244, 228)",
    "category": "cyan",
    "id": 150
  },
  {
    "hex": "#cef4e2",
    "rgb": "rgb(206, 244, 226)",
    "category": "cyan",
    "id": 151
  },
  {
    "hex": "#8edcb8",
    "rgb": "rgb(142, 220, 184)",
    "category": "cyan",
    "id": 152
  },
  {
    "hex": "#c4f4de",
    "rgb": "rgb(196, 244, 222)",
    "category": "cyan",
    "id": 153
  },
  {
    "hex": "#d2f5e6",
    "rgb": "rgb(210, 245, 230)",
    "category": "cyan",
    "id": 154
  },
  {
    "hex": "#82e5bc",
    "rgb": "rgb(130, 229, 188)",
    "category": "cyan",
    "id": 155
  },
  {
    "hex": "#9be4c7",
    "rgb": "rgb(155, 228, 199)",
    "category": "cyan",
    "id": 156
  },
  {
    "hex": "#aaeed4",
    "rgb": "rgb(170, 238, 212)",
    "category": "cyan",
    "id": 157
  },
  {
    "hex": "#acebd4",
    "rgb": "rgb(172, 235, 212)",
    "category": "cyan",
    "id": 158
  },
  {
    "hex": "#c1eede",
    "rgb": "rgb(193, 238, 222)",
    "category": "cyan",
    "id": 159
  },
  {
    "hex": "#a7ead4",
    "rgb": "rgb(167, 234, 212)",
    "category": "cyan",
    "id": 160
  },
  {
    "hex": "#8de4c8",
    "rgb": "rgb(141, 228, 200)",
    "category": "cyan",
    "id": 161
  },
  {
    "hex": "#b2efdd",
    "rgb": "rgb(178, 239, 221)",
    "category": "cyan",
    "id": 162
  },
  {
    "hex": "#95e5ce",
    "rgb": "rgb(149, 229, 206)",
    "category": "cyan",
    "id": 163
  },
  {
    "hex": "#b6f0e1",
    "rgb": "rgb(182, 240, 225)",
    "category": "cyan",
    "id": 164
  },
  {
    "hex": "#cef1e8",
    "rgb": "rgb(206, 241, 232)",
    "category": "cyan",
    "id": 165
  },
  {
    "hex": "#c7f0e7",
    "rgb": "rgb(199, 240, 231)",
    "category": "cyan",
    "id": 166
  },
  {
    "hex": "#bdebe1",
    "rgb": "rgb(189, 235, 225)",
    "category": "cyan",
    "id": 167
  },
  {
    "hex": "#cdf4ec",
    "rgb": "rgb(205, 244, 236)",
    "category": "cyan",
    "id": 168
  },
  {
    "hex": "#bdf1e8",
    "rgb": "rgb(189, 241, 232)",
    "category": "cyan",
    "id": 169
  },
  {
    "hex": "#a2ede1",
    "rgb": "rgb(162, 237, 225)",
    "category": "cyan",
    "id": 170
  },
  {
    "hex": "#99ecdf",
    "rgb": "rgb(153, 236, 223)",
    "category": "cyan",
    "id": 171
  },
  {
    "hex": "#c1f1ea",
    "rgb": "rgb(193, 241, 234)",
    "category": "cyan",
    "id": 172
  },
  {
    "hex": "#8ee0d7",
    "rgb": "rgb(142, 224, 215)",
    "category": "cyan",
    "id": 173
  },
  {
    "hex": "#94ece3",
    "rgb": "rgb(148, 236, 227)",
    "category": "cyan",
    "id": 174
  },
  {
    "hex": "#94e8e1",
    "rgb": "rgb(148, 232, 225)",
    "category": "cyan",
    "id": 175
  },
  {
    "hex": "#a4e8e3",
    "rgb": "rgb(164, 232, 227)",
    "category": "cyan",
    "id": 176
  },
  {
    "hex": "#aeeeeb",
    "rgb": "rgb(174, 238, 235)",
    "category": "cyan",
    "id": 177
  },
  {
    "hex": "#a3e5e3",
    "rgb": "rgb(163, 229, 227)",
    "category": "cyan",
    "id": 178
  },
  {
    "hex": "#8fe5e4",
    "rgb": "rgb(143, 229, 228)",
    "category": "cyan",
    "id": 179
  },
  {
    "hex": "#b4e8e8",
    "rgb": "rgb(180, 232, 232)",
    "category": "cyan",
    "id": 180
  },
  {
    "hex": "#caedee",
    "rgb": "rgb(202, 237, 238)",
    "category": "cyan",
    "id": 181
  },
  {
    "hex": "#d1f5f6",
    "rgb": "rgb(209, 245, 246)",
    "category": "cyan",
    "id": 182
  },
  {
    "hex": "#d1f0f1",
    "rgb": "rgb(209, 240, 241)",
    "category": "cyan",
    "id": 183
  },
  {
    "hex": "#a4e3e8",
    "rgb": "rgb(164, 227, 232)",
    "category": "cyan",
    "id": 184
  },
  {
    "hex": "#a9e8ed",
    "rgb": "rgb(169, 232, 237)",
    "category": "cyan",
    "id": 185
  },
  {
    "hex": "#bce9ee",
    "rgb": "rgb(188, 233, 238)",
    "category": "cyan",
    "id": 186
  },
  {
    "hex": "#afe0e6",
    "rgb": "rgb(175, 224, 230)",
    "category": "cyan",
    "id": 187
  },
  {
    "hex": "#d3f2f7",
    "rgb": "rgb(211, 242, 247)",
    "category": "cyan",
    "id": 188
  },
  {
    "hex": "#83d5e4",
    "rgb": "rgb(131, 213, 228)",
    "category": "cyan",
    "id": 189
  },
  {
    "hex": "#90d3e1",
    "rgb": "rgb(144, 211, 225)",
    "category": "cyan",
    "id": 190
  },
  {
    "hex": "#afdfea",
    "rgb": "rgb(175, 223, 234)",
    "category": "cyan",
    "id": 191
  },
  {
    "hex": "#a5d7e4",
    "rgb": "rgb(165, 215, 228)",
    "category": "cyan",
    "id": 192
  },
  {
    "hex": "#92d4e6",
    "rgb": "rgb(146, 212, 230)",
    "category": "cyan",
    "id": 193
  },
  {
    "hex": "#9dd4e4",
    "rgb": "rgb(157, 212, 228)",
    "category": "cyan",
    "id": 194
  },
  {
    "hex": "#cee9f2",
    "rgb": "rgb(206, 233, 242)",
    "category": "cyan",
    "id": 195
  },
  {
    "hex": "#d1ebf4",
    "rgb": "rgb(209, 235, 244)",
    "category": "cyan",
    "id": 196
  },
  {
    "hex": "#91c8dd",
    "rgb": "rgb(145, 200, 221)",
    "category": "cyan",
    "id": 197
  },
  {
    "hex": "#a6d2e5",
    "rgb": "rgb(166, 210, 229)",
    "category": "cyan",
    "id": 198
  },
  {
    "hex": "#d1e8f3",
    "rgb": "rgb(209, 232, 243)",
    "category": "cyan",
    "id": 199
  },
  {
    "hex": "#8ac2de",
    "rgb": "rgb(138, 194, 222)",
    "category": "cyan",
    "id": 200
  },
  {
    "hex": "#c0e1f3",
    "rgb": "rgb(192, 225, 243)",
    "category": "cyan",
    "id": 201
  },
  {
    "hex": "#a0d1ed",
    "rgb": "rgb(160, 209, 237)",
    "category": "cyan",
    "id": 202
  },
  {
    "hex": "#a2cde8",
    "rgb": "rgb(162, 205, 232)",
    "category": "cyan",
    "id": 203
  },
  {
    "hex": "#8dbfdf",
    "rgb": "rgb(141, 191, 223)",
    "category": "cyan",
    "id": 204
  },
  {
    "hex": "#8cc3eb",
    "rgb": "rgb(140, 195, 235)",
    "category": "cyan",
    "id": 205
  },
  {
    "hex": "#a6cfef",
    "rgb": "rgb(166, 207, 239)",
    "category": "cyan",
    "id": 206
  },
  {
    "hex": "#abcde9",
    "rgb": "rgb(171, 205, 233)",
    "category": "cyan",
    "id": 207
  },
  {
    "hex": "#87bbe9",
    "rgb": "rgb(135, 187, 233)",
    "category": "cyan",
    "id": 208
  },
  {
    "hex": "#c1daf2",
    "rgb": "rgb(193, 218, 242)",
    "category": "cyan",
    "id": 209
  },
  {
    "hex": "#84b4e3",
    "rgb": "rgb(132, 180, 227)",
    "category": "blue",
    "id": 210
  },
  {
    "hex": "#a8caee",
    "rgb": "rgb(168, 202, 238)",
    "category": "blue",
    "id": 211
  },
  {
    "hex": "#d3e4f7",
    "rgb": "rgb(211, 228, 247)",
    "category": "blue",
    "id": 212
  },
  {
    "hex": "#adc8e9",
    "rgb": "rgb(173, 200, 233)",
    "category": "blue",
    "id": 213
  },
  {
    "hex": "#9bbce6",
    "rgb": "rgb(155, 188, 230)",
    "category": "blue",
    "id": 214
  },
  {
    "hex": "#cbdbf2",
    "rgb": "rgb(203, 219, 242)",
    "category": "blue",
    "id": 215
  },
  {
    "hex": "#b4caeb",
    "rgb": "rgb(180, 202, 235)",
    "category": "blue",
    "id": 216
  },
  {
    "hex": "#8eb0e6",
    "rgb": "rgb(142, 176, 230)",
    "category": "blue",
    "id": 217
  },
  {
    "hex": "#d0dcf0",
    "rgb": "rgb(208, 220, 240)",
    "category": "blue",
    "id": 218
  },
  {
    "hex": "#bed0f2",
    "rgb": "rgb(190, 208, 242)",
    "category": "blue",
    "id": 219
  },
  {
    "hex": "#a0b7e5",
    "rgb": "rgb(160, 183, 229)",
    "category": "blue",
    "id": 220
  },
  {
    "hex": "#b6c6e9",
    "rgb": "rgb(182, 198, 233)",
    "category": "blue",
    "id": 221
  },
  {
    "hex": "#9db2e4",
    "rgb": "rgb(157, 178, 228)",
    "category": "blue",
    "id": 222
  },
  {
    "hex": "#a1b5e8",
    "rgb": "rgb(161, 181, 232)",
    "category": "blue",
    "id": 223
  },
  {
    "hex": "#c1cded",
    "rgb": "rgb(193, 205, 237)",
    "category": "blue",
    "id": 224
  },
  {
    "hex": "#c5cfec",
    "rgb": "rgb(197, 207, 236)",
    "category": "blue",
    "id": 225
  },
  {
    "hex": "#b5c3f2",
    "rgb": "rgb(181, 195, 242)",
    "category": "blue",
    "id": 226
  },
  {
    "hex": "#92a3e4",
    "rgb": "rgb(146, 163, 228)",
    "category": "blue",
    "id": 227
  },
  {
    "hex": "#a4b3ed",
    "rgb": "rgb(164, 179, 237)",
    "category": "blue",
    "id": 228
  },
  {
    "hex": "#97a4dd",
    "rgb": "rgb(151, 164, 221)",
    "category": "blue",
    "id": 229
  },
  {
    "hex": "#98a4e0",
    "rgb": "rgb(152, 164, 224)",
    "category": "blue",
    "id": 230
  },
  {
    "hex": "#a7b2ec",
    "rgb": "rgb(167, 178, 236)",
    "category": "blue",
    "id": 231
  },
  {
    "hex": "#8491e3",
    "rgb": "rgb(132, 145, 227)",
    "category": "blue",
    "id": 232
  },
  {
    "hex": "#d3d7f6",
    "rgb": "rgb(211, 215, 246)",
    "category": "blue",
    "id": 233
  },
  {
    "hex": "#838ce2",
    "rgb": "rgb(131, 140, 226)",
    "category": "blue",
    "id": 234
  },
  {
    "hex": "#cdd0f1",
    "rgb": "rgb(205, 208, 241)",
    "category": "blue",
    "id": 235
  },
  {
    "hex": "#afb4ef",
    "rgb": "rgb(175, 180, 239)",
    "category": "blue",
    "id": 236
  },
  {
    "hex": "#b2b5eb",
    "rgb": "rgb(178, 181, 235)",
    "category": "blue",
    "id": 237
  },
  {
    "hex": "#d5d6f4",
    "rgb": "rgb(213, 214, 244)",
    "category": "blue",
    "id": 238
  },
  {
    "hex": "#b5b5ea",
    "rgb": "rgb(181, 181, 234)",
    "category": "blue",
    "id": 239
  },
  {
    "hex": "#c5c5f2",
    "rgb": "rgb(197, 197, 242)",
    "category": "blue",
    "id": 240
  },
  {
    "hex": "#a4a3e4",
    "rgb": "rgb(164, 163, 228)",
    "category": "blue",
    "id": 241
  },
  {
    "hex": "#9491ea",
    "rgb": "rgb(148, 145, 234)",
    "category": "blue",
    "id": 242
  },
  {
    "hex": "#aca9e4",
    "rgb": "rgb(172, 169, 228)",
    "category": "blue",
    "id": 243
  },
  {
    "hex": "#aba7e7",
    "rgb": "rgb(171, 167, 231)",
    "category": "blue",
    "id": 244
  },
  {
    "hex": "#c8c4f2",
    "rgb": "rgb(200, 196, 242)",
    "category": "blue",
    "id": 245
  },
  {
    "hex": "#c1bcec",
    "rgb": "rgb(193, 188, 236)",
    "category": "blue",
    "id": 246
  },
  {
    "hex": "#9c92e9",
    "rgb": "rgb(156, 146, 233)",
    "category": "blue",
    "id": 247
  },
  {
    "hex": "#c2bceb",
    "rgb": "rgb(194, 188, 235)",
    "category": "blue",
    "id": 248
  },
  {
    "hex": "#bcb4eb",
    "rgb": "rgb(188, 180, 235)",
    "category": "blue",
    "id": 249
  },
  {
    "hex": "#a99de6",
    "rgb": "rgb(169, 157, 230)",
    "category": "blue",
    "id": 250
  },
  {
    "hex": "#c9c0f0",
    "rgb": "rgb(201, 192, 240)",
    "category": "blue",
    "id": 251
  },
  {
    "hex": "#c7bded",
    "rgb": "rgb(199, 189, 237)",
    "category": "blue",
    "id": 252
  },
  {
    "hex": "#9b86e8",
    "rgb": "rgb(155, 134, 232)",
    "category": "blue",
    "id": 253
  },
  {
    "hex": "#bdafec",
    "rgb": "rgb(189, 175, 236)",
    "category": "blue",
    "id": 254
  },
  {
    "hex": "#b9a8ea",
    "rgb": "rgb(185, 168, 234)",
    "category": "blue",
    "id": 255
  },
  {
    "hex": "#c1b1ef",
    "rgb": "rgb(193, 177, 239)",
    "category": "blue",
    "id": 256
  },
  {
    "hex": "#bdade7",
    "rgb": "rgb(189, 173, 231)",
    "category": "blue",
    "id": 257
  },
  {
    "hex": "#d6c9f4",
    "rgb": "rgb(214, 201, 244)",
    "category": "blue",
    "id": 258
  },
  {
    "hex": "#c5b3ec",
    "rgb": "rgb(197, 179, 236)",
    "category": "blue",
    "id": 259
  },
  {
    "hex": "#b095e6",
    "rgb": "rgb(176, 149, 230)",
    "category": "blue",
    "id": 260
  },
  {
    "hex": "#ad8de7",
    "rgb": "rgb(173, 141, 231)",
    "category": "blue",
    "id": 261
  },
  {
    "hex": "#aa8be1",
    "rgb": "rgb(170, 139, 225)",
    "category": "blue",
    "id": 262
  },
  {
    "hex": "#c3a9ed",
    "rgb": "rgb(195, 169, 237)",
    "category": "blue",
    "id": 263
  },
  {
    "hex": "#d6c6ee",
    "rgb": "rgb(214, 198, 238)",
    "category": "blue",
    "id": 264
  },
  {
    "hex": "#bb9fe2",
    "rgb": "rgb(187, 159, 226)",
    "category": "blue",
    "id": 265
  },
  {
    "hex": "#c1a6e4",
    "rgb": "rgb(193, 166, 228)",
    "category": "blue",
    "id": 266
  },
  {
    "hex": "#bf9ce9",
    "rgb": "rgb(191, 156, 233)",
    "category": "blue",
    "id": 267
  },
  {
    "hex": "#c6a4ed",
    "rgb": "rgb(198, 164, 237)",
    "category": "blue",
    "id": 268
  },
  {
    "hex": "#ceb2ec",
    "rgb": "rgb(206, 178, 236)",
    "category": "blue",
    "id": 269
  },
  {
    "hex": "#d5b8f2",
    "rgb": "rgb(213, 184, 242)",
    "category": "purple",
    "id": 270
  },
  {
    "hex": "#e0cdf3",
    "rgb": "rgb(224, 205, 243)",
    "category": "purple",
    "id": 271
  },
  {
    "hex": "#d5bbec",
    "rgb": "rgb(213, 187, 236)",
    "category": "purple",
    "id": 272
  },
  {
    "hex": "#bd91e1",
    "rgb": "rgb(189, 145, 225)",
    "category": "purple",
    "id": 273
  },
  {
    "hex": "#be91e0",
    "rgb": "rgb(190, 145, 224)",
    "category": "purple",
    "id": 274
  },
  {
    "hex": "#e7d2f6",
    "rgb": "rgb(231, 210, 246)",
    "category": "purple",
    "id": 275
  },
  {
    "hex": "#c698e5",
    "rgb": "rgb(198, 152, 229)",
    "category": "purple",
    "id": 276
  },
  {
    "hex": "#d8b4ee",
    "rgb": "rgb(216, 180, 238)",
    "category": "purple",
    "id": 277
  },
  {
    "hex": "#ca9be5",
    "rgb": "rgb(202, 155, 229)",
    "category": "purple",
    "id": 278
  },
  {
    "hex": "#c98bea",
    "rgb": "rgb(201, 139, 234)",
    "category": "purple",
    "id": 279
  },
  {
    "hex": "#c78ce4",
    "rgb": "rgb(199, 140, 228)",
    "category": "purple",
    "id": 280
  },
  {
    "hex": "#e4c5f3",
    "rgb": "rgb(228, 197, 243)",
    "category": "purple",
    "id": 281
  },
  {
    "hex": "#ecd3f6",
    "rgb": "rgb(236, 211, 246)",
    "category": "purple",
    "id": 282
  },
  {
    "hex": "#d8b0e8",
    "rgb": "rgb(216, 176, 232)",
    "category": "purple",
    "id": 283
  },
  {
    "hex": "#c984e2",
    "rgb": "rgb(201, 132, 226)",
    "category": "purple",
    "id": 284
  },
  {
    "hex": "#dfaeef",
    "rgb": "rgb(223, 174, 239)",
    "category": "purple",
    "id": 285
  },
  {
    "hex": "#d796eb",
    "rgb": "rgb(215, 150, 235)",
    "category": "purple",
    "id": 286
  },
  {
    "hex": "#e3c2ec",
    "rgb": "rgb(227, 194, 236)",
    "category": "purple",
    "id": 287
  },
  {
    "hex": "#eac6f3",
    "rgb": "rgb(234, 198, 243)",
    "category": "purple",
    "id": 288
  },
  {
    "hex": "#d090df",
    "rgb": "rgb(208, 144, 223)",
    "category": "purple",
    "id": 289
  },
  {
    "hex": "#dda0e9",
    "rgb": "rgb(221, 160, 233)",
    "category": "purple",
    "id": 290
  },
  {
    "hex": "#efcef4",
    "rgb": "rgb(239, 206, 244)",
    "category": "purple",
    "id": 291
  },
  {
    "hex": "#e4b1ec",
    "rgb": "rgb(228, 177, 236)",
    "category": "purple",
    "id": 292
  },
  {
    "hex": "#da95e3",
    "rgb": "rgb(218, 149, 227)",
    "category": "purple",
    "id": 293
  },
  {
    "hex": "#e59eed",
    "rgb": "rgb(229, 158, 237)",
    "category": "purple",
    "id": 294
  },
  {
    "hex": "#e7a9ed",
    "rgb": "rgb(231, 169, 237)",
    "category": "purple",
    "id": 295
  },
  {
    "hex": "#eec6f1",
    "rgb": "rgb(238, 198, 241)",
    "category": "purple",
    "id": 296
  },
  {
    "hex": "#dd98e1",
    "rgb": "rgb(221, 152, 225)",
    "category": "purple",
    "id": 297
  },
  {
    "hex": "#f1d8f2",
    "rgb": "rgb(241, 216, 242)",
    "category": "purple",
    "id": 298
  },
  {
    "hex": "#e784e9",
    "rgb": "rgb(231, 132, 233)",
    "category": "purple",
    "id": 299
  },
  {
    "hex": "#eaa5ea",
    "rgb": "rgb(234, 165, 234)",
    "category": "purple",
    "id": 300
  },
  {
    "hex": "#f6d1f6",
    "rgb": "rgb(246, 209, 246)",
    "category": "purple",
    "id": 301
  },
  {
    "hex": "#eda3eb",
    "rgb": "rgb(237, 163, 235)",
    "category": "purple",
    "id": 302
  },
  {
    "hex": "#e4a8e1",
    "rgb": "rgb(228, 168, 225)",
    "category": "purple",
    "id": 303
  },
  {
    "hex": "#e58fdf",
    "rgb": "rgb(229, 143, 223)",
    "category": "purple",
    "id": 304
  },
  {
    "hex": "#f3cdf0",
    "rgb": "rgb(243, 205, 240)",
    "category": "purple",
    "id": 305
  },
  {
    "hex": "#f6d2f2",
    "rgb": "rgb(246, 210, 242)",
    "category": "purple",
    "id": 306
  },
  {
    "hex": "#e19ad8",
    "rgb": "rgb(225, 154, 216)",
    "category": "purple",
    "id": 307
  },
  {
    "hex": "#efabe6",
    "rgb": "rgb(239, 171, 230)",
    "category": "purple",
    "id": 308
  },
  {
    "hex": "#df9ad5",
    "rgb": "rgb(223, 154, 213)",
    "category": "purple",
    "id": 309
  },
  {
    "hex": "#f2cbeb",
    "rgb": "rgb(242, 203, 235)",
    "category": "purple",
    "id": 310
  },
  {
    "hex": "#e094d2",
    "rgb": "rgb(224, 148, 210)",
    "category": "purple",
    "id": 311
  },
  {
    "hex": "#f1c5e8",
    "rgb": "rgb(241, 197, 232)",
    "category": "purple",
    "id": 312
  },
  {
    "hex": "#eaa3db",
    "rgb": "rgb(234, 163, 219)",
    "category": "purple",
    "id": 313
  },
  {
    "hex": "#e4a7d6",
    "rgb": "rgb(228, 167, 214)",
    "category": "purple",
    "id": 314
  },
  {
    "hex": "#e6abd7",
    "rgb": "rgb(230, 171, 215)",
    "category": "purple",
    "id": 315
  },
  {
    "hex": "#f3d5eb",
    "rgb": "rgb(243, 213, 235)",
    "category": "purple",
    "id": 316
  },
  {
    "hex": "#ea96d2",
    "rgb": "rgb(234, 150, 210)",
    "category": "purple",
    "id": 317
  },
  {
    "hex": "#ecb1da",
    "rgb": "rgb(236, 177, 218)",
    "category": "purple",
    "id": 318
  },
  {
    "hex": "#e986ca",
    "rgb": "rgb(233, 134, 202)",
    "category": "purple",
    "id": 319
  },
  {
    "hex": "#e190c6",
    "rgb": "rgb(225, 144, 198)",
    "category": "purple",
    "id": 320
  },
  {
    "hex": "#ecadd6",
    "rgb": "rgb(236, 173, 214)",
    "category": "purple",
    "id": 321
  },
  {
    "hex": "#eeb6da",
    "rgb": "rgb(238, 182, 218)",
    "category": "purple",
    "id": 322
  },
  {
    "hex": "#f4c6e2",
    "rgb": "rgb(244, 198, 226)",
    "category": "purple",
    "id": 323
  },
  {
    "hex": "#f3bede",
    "rgb": "rgb(243, 190, 222)",
    "category": "purple",
    "id": 324
  },
  {
    "hex": "#f1c9e1",
    "rgb": "rgb(241, 201, 225)",
    "category": "purple",
    "id": 325
  },
  {
    "hex": "#e2a3c7",
    "rgb": "rgb(226, 163, 199)",
    "category": "purple",
    "id": 326
  },
  {
    "hex": "#ecc5da",
    "rgb": "rgb(236, 197, 218)",
    "category": "purple",
    "id": 327
  },
  {
    "hex": "#ea98c4",
    "rgb": "rgb(234, 152, 196)",
    "category": "purple",
    "id": 328
  },
  {
    "hex": "#f5d2e4",
    "rgb": "rgb(245, 210, 228)",
    "category": "purple",
    "id": 329
  },
  {
    "hex": "#ebb4d0",
    "rgb": "rgb(235, 180, 208)",
    "category": "red",
    "id": 330
  },
  {
    "hex": "#e6adc8",
    "rgb": "rgb(230, 173, 200)",
    "category": "red",
    "id": 331
  },
  {
    "hex": "#eca2c5",
    "rgb": "rgb(236, 162, 197)",
    "category": "red",
    "id": 332
  },
  {
    "hex": "#f1d0df",
    "rgb": "rgb(241, 208, 223)",
    "category": "red",
    "id": 333
  },
  {
    "hex": "#eb9abd",
    "rgb": "rgb(235, 154, 189)",
    "category": "red",
    "id": 334
  },
  {
    "hex": "#f1c1d5",
    "rgb": "rgb(241, 193, 213)",
    "category": "red",
    "id": 335
  },
  {
    "hex": "#e680a9",
    "rgb": "rgb(230, 128, 169)",
    "category": "red",
    "id": 336
  },
  {
    "hex": "#f3bfd3",
    "rgb": "rgb(243, 191, 211)",
    "category": "red",
    "id": 337
  },
  {
    "hex": "#f3c5d6",
    "rgb": "rgb(243, 197, 214)",
    "category": "red",
    "id": 338
  },
  {
    "hex": "#e695b1",
    "rgb": "rgb(230, 149, 177)",
    "category": "red",
    "id": 339
  },
  {
    "hex": "#e48aa8",
    "rgb": "rgb(228, 138, 168)",
    "category": "red",
    "id": 340
  },
  {
    "hex": "#ebb5c6",
    "rgb": "rgb(235, 181, 198)",
    "category": "red",
    "id": 341
  },
  {
    "hex": "#f2c9d5",
    "rgb": "rgb(242, 201, 213)",
    "category": "red",
    "id": 342
  },
  {
    "hex": "#f2c7d3",
    "rgb": "rgb(242, 199, 211)",
    "category": "red",
    "id": 343
  },
  {
    "hex": "#e8aabb",
    "rgb": "rgb(232, 170, 187)",
    "category": "red",
    "id": 344
  },
  {
    "hex": "#f4d1da",
    "rgb": "rgb(244, 209, 218)",
    "category": "red",
    "id": 345
  },
  {
    "hex": "#e8a1b2",
    "rgb": "rgb(232, 161, 178)",
    "category": "red",
    "id": 346
  },
  {
    "hex": "#efc7cf",
    "rgb": "rgb(239, 199, 207)",
    "category": "red",
    "id": 347
  },
  {
    "hex": "#eeabb9",
    "rgb": "rgb(238, 171, 185)",
    "category": "red",
    "id": 348
  },
  {
    "hex": "#f6d3d9",
    "rgb": "rgb(246, 211, 217)",
    "category": "red",
    "id": 349
  },
  {
    "hex": "#f2c8cf",
    "rgb": "rgb(242, 200, 207)",
    "category": "red",
    "id": 350
  },
  {
    "hex": "#ebaab4",
    "rgb": "rgb(235, 170, 180)",
    "category": "red",
    "id": 351
  },
  {
    "hex": "#eec4c9",
    "rgb": "rgb(238, 196, 201)",
    "category": "red",
    "id": 352
  },
  {
    "hex": "#f3d0d4",
    "rgb": "rgb(243, 208, 212)",
    "category": "red",
    "id": 353
  },
  {
    "hex": "#e9858f",
    "rgb": "rgb(233, 133, 143)",
    "category": "red",
    "id": 354
  },
  {
    "hex": "#dc8f96",
    "rgb": "rgb(220, 143, 150)",
    "category": "red",
    "id": 355
  },
  {
    "hex": "#e6adb1",
    "rgb": "rgb(230, 173, 177)",
    "category": "red",
    "id": 356
  },
  {
    "hex": "#db8d91",
    "rgb": "rgb(219, 141, 145)",
    "category": "red",
    "id": 357
  },
  {
    "hex": "#f1d4d5",
    "rgb": "rgb(241, 212, 213)",
    "category": "red",
    "id": 358
  },
  {
    "hex": "#f4cecf",
    "rgb": "rgb(244, 206, 207)",
    "category": "red",
    "id": 359
  },
  {
    "hex": "#ed9898",
    "rgb": "rgb(237, 152, 152)",
    "category": "red",
    "id": 360
  }
]